swiggy_order/__init__.py
swiggy_order/apis/__init__.py
swiggy_order/constants.py
swiggy_order/utils.py
swiggy_order-1.0.0.dist-info/entry_points.txt
swiggy_order-1.0.0.dist-info/WHEEL
swiggy_order-1.0.0.dist-info/METADATA
swiggy_order-1.0.0.dist-info/RECORD
